clay/__init__.py
clay/cli.py
clay/main.py
clay/server.py
clay/blueprint/README.md
clay/blueprint/_index.html
clay/blueprint/clay.yaml
clay/blueprint/favicon.ico
clay/blueprint/humans.txt
clay/blueprint/index.html
clay/blueprint/not-found.html
clay/blueprint/robots.txt
clay/blueprint/_layouts/default.html
clay/blueprint/static/favicon.svg
clay/blueprint/static/normalize.css
clay/blueprint/static/not-found.css
clay/blueprint/static/scripts.js
clay/blueprint/static/styles.css
clay/utils/__init__.py
clay/utils/active.py
clay/utils/binaries.py
clay/utils/blueprint_render.py
clay/utils/jinja_includewith.py
clay/utils/jinja_render.py
clay/utils/load_config.py
clay/utils/make_matcher.py
clay/utils/multidict.py
clay/utils/name_generator.py
clay/utils/request.py
clay/utils/urls.py
clay/utils/vcs.py
clay-4.6.2.dist-info/METADATA
clay-4.6.2.dist-info/MIT-LICENSE
clay-4.6.2.dist-info/WHEEL
clay-4.6.2.dist-info/entry_points.txt
clay-4.6.2.dist-info/top_level.txt
clay-4.6.2.dist-info/RECORD
