Metadata-Version: 2.1
Name: clay
Version: 4.6.2
Summary: An amazing web prototyping tool.
Home-page: http://lucuma.github.io/clay/
Author: Juan-Pablo Scaletti
Author-email: juanpablo@jpscaletti.com
License: MIT
Project-URL: Documentation, http://lucuma.github.io/clay/
Project-URL: Issue tracker, https://github.com/lucuma/clay/issues
Classifier: Development Status :: 4 - Beta
Classifier: Environment :: Web Environment
Classifier: License :: OSI Approved :: MIT License
Classifier: Programming Language :: Python :: 3 :: Only
Classifier: Programming Language :: Python :: 3.7
Classifier: Programming Language :: Python :: 3.8
Classifier: Programming Language :: Python :: 3.9
Classifier: Programming Language :: Python :: 3.10
Requires-Python: <4.0,>=3.7
License-File: MIT-LICENSE
Requires-Dist: gunicorn (~=20.0)
Requires-Dist: jinja2 (~=3.0)
Requires-Dist: multipart (>=0.2.4)
Requires-Dist: proper-cli (~=1.0)
Requires-Dist: pyyaml (~=5.1)
Requires-Dist: whitenoise (~=4.1)
Provides-Extra: dev
Requires-Dist: black ; extra == 'dev'
Requires-Dist: tox ; extra == 'dev'
Provides-Extra: test
Requires-Dist: flake8 ; extra == 'test'
Requires-Dist: flake8-bugbear ; extra == 'test'
Requires-Dist: flake8-logging-format ; extra == 'test'
Requires-Dist: flake8-quotes ; extra == 'test'
Requires-Dist: pytest ; extra == 'test'
Requires-Dist: pytest-cov ; extra == 'test'
Requires-Dist: webtest ; extra == 'test'
